MLBuddy/__init__.py
MLBuddy/model_selection.py
MLBuddy/predictor.py
MLBuddy/preprocessing.py
MLBuddy/models/__init__.py
MLBuddy/models/classification.py
MLBuddy/models/regression.py
mlbuddy-0.1.0.dist-info/licenses/LICENSE.txt
mlbuddy-0.1.0.dist-info/METADATA
mlbuddy-0.1.0.dist-info/WHEEL
mlbuddy-0.1.0.dist-info/top_level.txt
mlbuddy-0.1.0.dist-info/RECORD
