Metadata-Version: 2.4
Name: MLBuddy
Version: 0.1.0
Summary: A simple AutoML library
Author: Neilansh Chauhan
Author-email: neilanshchauhan4@gmail.com
License: MIT
Classifier: License :: OSI Approved :: MIT License
Classifier: Programming Language :: Python :: 3
Classifier: Programming Language :: Python :: 3.7
Classifier: Programming Language :: Python :: 3.8
Classifier: Programming Language :: Python :: 3.9
Classifier: Programming Language :: Python :: 3.10
Classifier: Operating System :: OS Independent
Requires-Python: >=3.7
License-File: LICENSE.txt
Requires-Dist: pandas>=1.3.0
Requires-Dist: numpy>=1.20.0
Requires-Dist: scikit-learn>=1.0.0
Requires-Dist: tqdm>=4.62.0
Requires-Dist: lightgbm>=3.3.0
Requires-Dist: xgboost>=1.5.0
Requires-Dist: seaborn>=0.11.0
Requires-Dist: matplotlib>=3.4.0
Dynamic: author
Dynamic: author-email
Dynamic: classifier
Dynamic: description
Dynamic: description-content-type
Dynamic: license
Dynamic: license-file
Dynamic: requires-dist
Dynamic: requires-python
Dynamic: summary
